[{"song_id":"2130872","album_id":"172431","name":"Drug","style":null,"track":"1","artist_name":"The Czars","artist_id":"24214","lyric":"http://img.xiami.net/lyric/upload/72/2130872_1298702982.lrc","inkui_url":"/24214/172431/2130872.mp3","songwriters":"","composer":"","threads_count":"1","posts_count":"0","listen_file":"/aliyunos/214/24214/172431/2130872_106912_l.mp3","lyric_url":"0","has_resource":null,"cd_serial":"1","sub_title":"","complete":"1","singers":"The Czars","arrangement":"","default_resource_id":"106912","lyric_file":null,"title_url":"The+Ugly+People+Vs.+","length":"250","recommends":"240","title":"The Ugly People Vs. The Beautiful People","gmt_publish":"1003161600","picture":null,"song_count":"12","language":"英语","publishtime":null,"inkui_img_url":null,"company":"Manifesto","disc_code":"","rank":"23","album_logo":"http://img.xiami.net/images/album/img14/24214/1724311351133261_2.jpg","is_check":"0","category":null,"status":"1","album_url":null,"category_name":null,"cd_count":"1","is_play":"1","uploader":null,"gmt_upload":"0","is_exported":"0","editor":"tangxiaoqing","gmt_add":"1216353423","gmt_last_modified":"1351133261","key_words":" ","tags":null,"tw_top":"0","crawler":null,"xiami_pub_id":"0","collects":"570","play_count":"104125","pub_bitrate":"0","genre_id":null,"encode_rate":"0","location":"http://m1.file.xiami.com/214/24214/172431/2130872_106912_l.mp3","low_size":"6011089","file_size":null,"low_hash":"fa2df0bd7e72a1fc74dfbfc7f0fd0aca","whole_hash":"fa2df0bd7e72a1fc74dfbfc7f0fd0aca","content_hash":"fa2df0bd7e72a1fc74dfbfc7f0fd0aca","content_size":"6011089","lock_lrc":"2","year_play":"81877","grade":"-1"},{"song_id":"2130873","album_id":"172431","name":"Side Effect","style":null,"track":"2","artist_name":"The Czars","artist_id":"24214","lyric":null,"inkui_url":"/24214/172431/2130873.mp3","songwriters":"","composer":"","threads_count":"1","posts_count":"0","listen_file":"/aliyunos/214/24214/172431/2130873_106913_l.mp3","lyric_url":"0","has_resource":null,"cd_serial":"1","sub_title":"","complete":"1","singers":"The Czars","arrangement":"","default_resource_id":"106913","lyric_file":null,"title_url":"The+Ugly+People+Vs.+","length":"296","recommends":"240","title":"The Ugly People Vs. The Beautiful People","gmt_publish":"1003161600","picture":null,"song_count":"12","language":"英语","publishtime":null,"inkui_img_url":null,"company":"Manifesto","disc_code":"","rank":"23","album_logo":"http://img.xiami.net/images/album/img14/24214/1724311351133261_2.jpg","is_check":"0","category":null,"status":"1","album_url":null,"category_name":null,"cd_count":"1","is_play":"1","uploader":null,"gmt_upload":"0","is_exported":"0","editor":"tangxiaoqing","gmt_add":"1216353423","gmt_last_modified":"1351133261","key_words":" ","tags":null,"tw_top":"0","crawler":null,"xiami_pub_id":"0","collects":"570","play_count":"104125","pub_bitrate":"0","genre_id":null,"encode_rate":"0","location":"http://m1.file.xiami.com/214/24214/172431/2130873_106913_l.mp3","low_size":"7100708","file_size":null,"low_hash":"e1bcffa00e8877ec27d081b91467b101","whole_hash":"e1bcffa00e8877ec27d081b91467b101","content_hash":"e1bcffa00e8877ec27d081b91467b101","content_size":"7100708","lock_lrc":"2","year_play":"2150","grade":"-1"},{"song_id":"2130874","album_id":"172431","name":"Killjoy","style":null,"track":"3","artist_name":"The Czars","artist_id":"24214","lyric":"http://img.xiami.net/lyric/upload/74/2130874_1286684707.txt","inkui_url":"/24214/172431/2130874.mp3","songwriters":"","composer":"","threads_count":"1","posts_count":"0","listen_file":"/aliyunos/214/24214/172431/2130874_106914_l.mp3","lyric_url":"0","has_resource":null,"cd_serial":"1","sub_title":"","complete":"1","singers":"The Czars","arrangement":"","default_resource_id":"106914","lyric_file":null,"title_url":"The+Ugly+People+Vs.+","length":"341","recommends":"240","title":"The Ugly People Vs. The Beautiful People","gmt_publish":"1003161600","picture":null,"song_count":"12","language":"英语","publishtime":null,"inkui_img_url":null,"company":"Manifesto","disc_code":"","rank":"23","album_logo":"http://img.xiami.net/images/album/img14/24214/1724311351133261_2.jpg","is_check":"0","category":null,"status":"1","album_url":null,"category_name":null,"cd_count":"1","is_play":"1","uploader":null,"gmt_upload":"0","is_exported":"0","editor":"tangxiaoqing","gmt_add":"1216353423","gmt_last_modified":"1351133261","key_words":" ","tags":null,"tw_top":"0","crawler":null,"xiami_pub_id":"0","collects":"570","play_count":"104125","pub_bitrate":"0","genre_id":null,"encode_rate":"0","location":"http://m1.file.xiami.com/214/24214/172431/2130874_106914_l.mp3","low_size":"8172773","file_size":null,"low_hash":"b7bc75d92cc1f4d34ad65cd21176bc7b","whole_hash":"b7bc75d92cc1f4d34ad65cd21176bc7b","content_hash":"b7bc75d92cc1f4d34ad65cd21176bc7b","content_size":"8172773","lock_lrc":"2","year_play":"9127","grade":"-1"},{"song_id":"2130875","album_id":"172431","name":"Caterpillar","style":null,"track":"4","artist_name":"The Czars","artist_id":"24214","lyric":null,"inkui_url":"/24214/172431/2130875.mp3","songwriters":"","composer":"","threads_count":"1","posts_count":"0","listen_file":"/aliyunos/214/24214/172431/2130875_106915_l.mp3","lyric_url":"0","has_resource":null,"cd_serial":"1","sub_title":"","complete":"1","singers":"The Czars","arrangement":"","default_resource_id":"106915","lyric_file":null,"title_url":"The+Ugly+People+Vs.+","length":"403","recommends":"240","title":"The Ugly People Vs. The Beautiful People","gmt_publish":"1003161600","picture":null,"song_count":"12","language":"英语","publishtime":null,"inkui_img_url":null,"company":"Manifesto","disc_code":"","rank":"23","album_logo":"http://img.xiami.net/images/album/img14/24214/1724311351133261_2.jpg","is_check":"0","category":null,"status":"1","album_url":null,"category_name":null,"cd_count":"1","is_play":"1","uploader":null,"gmt_upload":"0","is_exported":"0","editor":"tangxiaoqing","gmt_add":"1216353423","gmt_last_modified":"1351133261","key_words":" ","tags":null,"tw_top":"0","crawler":null,"xiami_pub_id":"0","collects":"570","play_count":"104125","pub_bitrate":"0","genre_id":null,"encode_rate":"0","location":"http://m1.file.xiami.com/214/24214/172431/2130875_106915_l.mp3","low_size":"9670530","file_size":null,"low_hash":"dea9bfc568b2608747d4a3bef5c9bb8c","whole_hash":"dea9bfc568b2608747d4a3bef5c9bb8c","content_hash":"dea9bfc568b2608747d4a3bef5c9bb8c","content_size":"9670530","lock_lrc":"2","year_play":"1426","grade":"-1"},{"song_id":"2130876","album_id":"172431","name":"Lullaby 6000","style":null,"track":"5","artist_name":"The Czars","artist_id":"24214","lyric":null,"inkui_url":"/24214/172431/2130876.mp3","songwriters":"","composer":"","threads_count":"1","posts_count":"0","listen_file":"/aliyunos/214/24214/172431/2130876_106916_l.mp3","lyric_url":"0","has_resource":null,"cd_serial":"1","sub_title":"","complete":"1","singers":"The Czars","arrangement":"","default_resource_id":"106916","lyric_file":null,"title_url":"The+Ugly+People+Vs.+","length":"335","recommends":"240","title":"The Ugly People Vs. The Beautiful People","gmt_publish":"1003161600","picture":null,"song_count":"12","language":"英语","publishtime":null,"inkui_img_url":null,"company":"Manifesto","disc_code":"","rank":"23","album_logo":"http://img.xiami.net/images/album/img14/24214/1724311351133261_2.jpg","is_check":"0","category":null,"status":"1","album_url":null,"category_name":null,"cd_count":"1","is_play":"1","uploader":null,"gmt_upload":"0","is_exported":"0","editor":"tangxiaoqing","gmt_add":"1216353423","gmt_last_modified":"1351133261","key_words":" ","tags":null,"tw_top":"0","crawler":null,"xiami_pub_id":"0","collects":"570","play_count":"104125","pub_bitrate":"0","genre_id":null,"encode_rate":"0","location":"http://m1.file.xiami.com/214/24214/172431/2130876_106916_l.mp3","low_size":"8050520","file_size":null,"low_hash":"0a179eb7c18ae4cf309077905428c95a","whole_hash":"0a179eb7c18ae4cf309077905428c95a","content_hash":"0a179eb7c18ae4cf309077905428c95a","content_size":"8050520","lock_lrc":"2","year_play":"1046","grade":"-1"},{"song_id":"2130877","album_id":"172431","name":"This","style":null,"track":"6","artist_name":"The Czars","artist_id":"24214","lyric":null,"inkui_url":"/24214/172431/2130877.mp3","songwriters":"","composer":"","threads_count":"1","posts_count":"0","listen_file":"/aliyunos/214/24214/172431/2130877_106917_l.mp3","lyric_url":"0","has_resource":null,"cd_serial":"1","sub_title":"","complete":"1","singers":"The Czars","arrangement":"","default_resource_id":"106917","lyric_file":null,"title_url":"The+Ugly+People+Vs.+","length":"292","recommends":"240","title":"The Ugly People Vs. The Beautiful People","gmt_publish":"1003161600","picture":null,"song_count":"12","language":"英语","publishtime":null,"inkui_img_url":null,"company":"Manifesto","disc_code":"","rank":"23","album_logo":"http://img.xiami.net/images/album/img14/24214/1724311351133261_2.jpg","is_check":"0","category":null,"status":"1","album_url":null,"category_name":null,"cd_count":"1","is_play":"1","uploader":null,"gmt_upload":"0","is_exported":"0","editor":"tangxiaoqing","gmt_add":"1216353423","gmt_last_modified":"1351133261","key_words":" ","tags":null,"tw_top":"0","crawler":null,"xiami_pub_id":"0","collects":"570","play_count":"104125","pub_bitrate":"0","genre_id":null,"encode_rate":"0","location":"http://m1.file.xiami.com/214/24214/172431/2130877_106917_l.mp3","low_size":"7021087","file_size":null,"low_hash":"b061d5436da9479183a8b0f8338c3a3e","whole_hash":"b061d5436da9479183a8b0f8338c3a3e","content_hash":"b061d5436da9479183a8b0f8338c3a3e","content_size":"7021087","lock_lrc":null,"year_play":"944","grade":"-1"},{"song_id":"2130878","album_id":"172431","name":"Autumn","style":null,"track":"7","artist_name":"The Czars","artist_id":"24214","lyric":null,"inkui_url":"/24214/172431/2130878.mp3","songwriters":"","composer":"","threads_count":"1","posts_count":"0","listen_file":"/aliyunos/214/24214/172431/2130878_106918_l.mp3","lyric_url":"0","has_resource":null,"cd_serial":"1","sub_title":"","complete":"1","singers":"The Czars","arrangement":"","default_resource_id":"106918","lyric_file":null,"title_url":"The+Ugly+People+Vs.+","length":"246","recommends":"240","title":"The Ugly People Vs. The Beautiful People","gmt_publish":"1003161600","picture":null,"song_count":"12","language":"英语","publishtime":null,"inkui_img_url":null,"company":"Manifesto","disc_code":"","rank":"23","album_logo":"http://img.xiami.net/images/album/img14/24214/1724311351133261_2.jpg","is_check":"0","category":null,"status":"1","album_url":null,"category_name":null,"cd_count":"1","is_play":"1","uploader":null,"gmt_upload":"0","is_exported":"0","editor":"tangxiaoqing","gmt_add":"1216353423","gmt_last_modified":"1351133261","key_words":" ","tags":null,"tw_top":"0","crawler":null,"xiami_pub_id":"0","collects":"570","play_count":"104125","pub_bitrate":"0","genre_id":null,"encode_rate":"0","location":"http://m1.file.xiami.com/214/24214/172431/2130878_106918_l.mp3","low_size":"5915794","file_size":null,"low_hash":"f63cb5e70d9c9a7034b34154f473d6b7","whole_hash":"f63cb5e70d9c9a7034b34154f473d6b7","content_hash":"f63cb5e70d9c9a7034b34154f473d6b7","content_size":"5915794","lock_lrc":null,"year_play":"976","grade":"-1"},{"song_id":"2130879","album_id":"172431","name":"Black and Blue","style":null,"track":"8","artist_name":"The Czars","artist_id":"24214","lyric":"http://img.xiami.net/lyric/upload/79/2130879_1299088214.lrc","inkui_url":"/24214/172431/2130879.mp3","songwriters":"","composer":"","threads_count":"1","posts_count":"0","listen_file":"/aliyunos/214/24214/172431/2130879_106919_l.mp3","lyric_url":"0","has_resource":null,"cd_serial":"1","sub_title":"","complete":"1","singers":"The Czars","arrangement":"","default_resource_id":"106919","lyric_file":null,"title_url":"The+Ugly+People+Vs.+","length":"315","recommends":"240","title":"The Ugly People Vs. The Beautiful People","gmt_publish":"1003161600","picture":null,"song_count":"12","language":"英语","publishtime":null,"inkui_img_url":null,"company":"Manifesto","disc_code":"","rank":"23","album_logo":"http://img.xiami.net/images/album/img14/24214/1724311351133261_2.jpg","is_check":"0","category":null,"status":"1","album_url":null,"category_name":null,"cd_count":"1","is_play":"1","uploader":null,"gmt_upload":"0","is_exported":"0","editor":"tangxiaoqing","gmt_add":"1216353423","gmt_last_modified":"1351133261","key_words":" ","tags":null,"tw_top":"0","crawler":null,"xiami_pub_id":"0","collects":"570","play_count":"104125","pub_bitrate":"0","genre_id":null,"encode_rate":"0","location":"http://m1.file.xiami.com/214/24214/172431/2130879_106919_l.mp3","low_size":"7565270","file_size":null,"low_hash":"c3ca277a35df4f295d7d1e2378e031b2","whole_hash":"c3ca277a35df4f295d7d1e2378e031b2","content_hash":"c3ca277a35df4f295d7d1e2378e031b2","content_size":"7565270","lock_lrc":"2","year_play":"4185","grade":"-1"},{"song_id":"2130880","album_id":"172431","name":"Anger","style":null,"track":"9","artist_name":"The Czars","artist_id":"24214","lyric":null,"inkui_url":"/24214/172431/2130880.mp3","songwriters":"","composer":"","threads_count":"1","posts_count":"0","listen_file":"/aliyunos/214/24214/172431/2130880_106920_l.mp3","lyric_url":"0","has_resource":null,"cd_serial":"1","sub_title":"","complete":"1","singers":"The Czars","arrangement":"","default_resource_id":"106920","lyric_file":null,"title_url":"The+Ugly+People+Vs.+","length":"267","recommends":"240","title":"The Ugly People Vs. The Beautiful People","gmt_publish":"1003161600","picture":null,"song_count":"12","language":"英语","publishtime":null,"inkui_img_url":null,"company":"Manifesto","disc_code":"","rank":"23","album_logo":"http://img.xiami.net/images/album/img14/24214/1724311351133261_2.jpg","is_check":"0","category":null,"status":"1","album_url":null,"category_name":null,"cd_count":"1","is_play":"1","uploader":null,"gmt_upload":"0","is_exported":"0","editor":"tangxiaoqing","gmt_add":"1216353423","gmt_last_modified":"1351133261","key_words":" ","tags":null,"tw_top":"0","crawler":null,"xiami_pub_id":"0","collects":"570","play_count":"104125","pub_bitrate":"0","genre_id":null,"encode_rate":"0","location":"http://m1.file.xiami.com/214/24214/172431/2130880_106920_l.mp3","low_size":"6403552","file_size":null,"low_hash":"735844eead128a617a140cab5d1ce0f8","whole_hash":"735844eead128a617a140cab5d1ce0f8","content_hash":"735844eead128a617a140cab5d1ce0f8","content_size":"6403552","lock_lrc":null,"year_play":"745","grade":"-1"},{"song_id":"2130881","album_id":"172431","name":"Roger\u0026#039;s Song","style":null,"track":"10","artist_name":"The Czars","artist_id":"24214","lyric":null,"inkui_url":"/24214/172431/2130881.mp3","songwriters":"","composer":"","threads_count":"1","posts_count":"0","listen_file":"/aliyunos/214/24214/172431/2130881_106921_l.mp3","lyric_url":"0","has_resource":null,"cd_serial":"1","sub_title":"","complete":"1","singers":"The Czars","arrangement":"","default_resource_id":"106921","lyric_file":null,"title_url":"The+Ugly+People+Vs.+","length":"209","recommends":"240","title":"The Ugly People Vs. The Beautiful People","gmt_publish":"1003161600","picture":null,"song_count":"12","language":"英语","publishtime":null,"inkui_img_url":null,"company":"Manifesto","disc_code":"","rank":"23","album_logo":"http://img.xiami.net/images/album/img14/24214/1724311351133261_2.jpg","is_check":"0","category":null,"status":"1","album_url":null,"category_name":null,"cd_count":"1","is_play":"1","uploader":null,"gmt_upload":"0","is_exported":"0","editor":"tangxiaoqing","gmt_add":"1216353423","gmt_last_modified":"1351133261","key_words":" ","tags":null,"tw_top":"0","crawler":null,"xiami_pub_id":"0","collects":"570","play_count":"104125","pub_bitrate":"0","genre_id":null,"encode_rate":"0","location":"http://m1.file.xiami.com/214/24214/172431/2130881_106921_l.mp3","low_size":"5015510","file_size":null,"low_hash":"fad739ced51370966e92f4ae96d15ff9","whole_hash":"fad739ced51370966e92f4ae96d15ff9","content_hash":"fad739ced51370966e92f4ae96d15ff9","content_size":"5015510","lock_lrc":null,"year_play":"509","grade":"-1"},{"song_id":"2130882","album_id":"172431","name":"What Used to Be a Human","style":null,"track":"11","artist_name":"The Czars","artist_id":"24214","lyric":null,"inkui_url":"/24214/172431/2130882.mp3","songwriters":"","composer":"","threads_count":"1","posts_count":"0","listen_file":"/aliyunos/214/24214/172431/2130882_106922_l.mp3","lyric_url":"0","has_resource":null,"cd_serial":"1","sub_title":"","complete":"1","singers":"The Czars","arrangement":"","default_resource_id":"106922","lyric_file":null,"title_url":"The+Ugly+People+Vs.+","length":"426","recommends":"240","title":"The Ugly People Vs. The Beautiful People","gmt_publish":"1003161600","picture":null,"song_count":"12","language":"英语","publishtime":null,"inkui_img_url":null,"company":"Manifesto","disc_code":"","rank":"23","album_logo":"http://img.xiami.net/images/album/img14/24214/1724311351133261_2.jpg","is_check":"0","category":null,"status":"1","album_url":null,"category_name":null,"cd_count":"1","is_play":"1","uploader":null,"gmt_upload":"0","is_exported":"0","editor":"tangxiaoqing","gmt_add":"1216353423","gmt_last_modified":"1351133261","key_words":" ","tags":null,"tw_top":"0","crawler":null,"xiami_pub_id":"0","collects":"570","play_count":"104125","pub_bitrate":"0","genre_id":null,"encode_rate":"0","location":"http://m1.file.xiami.com/214/24214/172431/2130882_106922_l.mp3","low_size":"10220982","file_size":null,"low_hash":"eb59e05798ca37b55c7feaf0e1c5f49b","whole_hash":"eb59e05798ca37b55c7feaf0e1c5f49b","content_hash":"eb59e05798ca37b55c7feaf0e1c5f49b","content_size":"10220982","lock_lrc":null,"year_play":"615","grade":"-1"},{"song_id":"2130883","album_id":"172431","name":"Catherine","style":null,"track":"12","artist_name":"The Czars","artist_id":"24214","lyric":null,"inkui_url":"/24214/172431/2130883.mp3","songwriters":"","composer":"","threads_count":"1","posts_count":"0","listen_file":"/aliyunos/214/24214/172431/2130883_106923_l.mp3","lyric_url":"0","has_resource":null,"cd_serial":"1","sub_title":"","complete":"1","singers":"The Czars","arrangement":"","default_resource_id":"106923","lyric_file":null,"title_url":"The+Ugly+People+Vs.+","length":"256","recommends":"240","title":"The Ugly People Vs. The Beautiful People","gmt_publish":"1003161600","picture":null,"song_count":"12","language":"英语","publishtime":null,"inkui_img_url":null,"company":"Manifesto","disc_code":"","rank":"23","album_logo":"http://img.xiami.net/images/album/img14/24214/1724311351133261_2.jpg","is_check":"0","category":null,"status":"1","album_url":null,"category_name":null,"cd_count":"1","is_play":"1","uploader":null,"gmt_upload":"0","is_exported":"0","editor":"tangxiaoqing","gmt_add":"1216353423","gmt_last_modified":"1351133261","key_words":" ","tags":null,"tw_top":"0","crawler":null,"xiami_pub_id":"0","collects":"570","play_count":"104125","pub_bitrate":"0","genre_id":null,"encode_rate":"0","location":"http://m1.file.xiami.com/214/24214/172431/2130883_106923_l.mp3","low_size":"6144000","file_size":null,"low_hash":"76f4ea5459ba0b48481678f397ae9986","whole_hash":"76f4ea5459ba0b48481678f397ae9986","content_hash":"76f4ea5459ba0b48481678f397ae9986","content_size":"6144000","lock_lrc":null,"year_play":"525","grade":"-1"}]