[{"song_id":"1770874352","album_id":"78399","name":"The Reverse (Alternate Version 1)","style":null,"track":"1","artist_name":"Archie Shepp","artist_id":"11392","lyric":null,"inkui_url":"/11392/78399/1770874352.mp3","songwriters":"","composer":"","threads_count":"0","posts_count":"0","listen_file":"/aliyunos/392/11392/78399/1770874352_3235168_l.mp3","lyric_url":"0","has_resource":null,"cd_serial":"1","sub_title":null,"complete":"1","singers":"Archie Shepp","arrangement":"","default_resource_id":"3235168","lyric_file":null,"title_url":"Gemini","length":"257","recommends":"3","title":"Gemini","gmt_publish":"1183910400","picture":null,"song_count":"16","language":"英语","publishtime":"Jul 9, 2007","inkui_img_url":null,"company":"Archie Ball","disc_code":"","rank":"0","album_logo":"http://img.xiami.net/./res/img/default/cd55.gif","is_check":"0","category":null,"status":"1","album_url":"/cg/amg.dll?p=amg\u0026amp;sql=10:j9fixzqgldte","category_name":null,"cd_count":"2","is_play":"1","uploader":null,"gmt_upload":"0","is_exported":"0","editor":null,"gmt_add":"0","gmt_last_modified":"0","key_words":" ","tags":";","tw_top":"0","crawler":null,"xiami_pub_id":"294444","collects":"10","play_count":"56","pub_bitrate":"0","genre_id":null,"encode_rate":"0","location":"http://m1.file.xiami.com/392/11392/78399/1770874352_3235168_l.mp3","low_size":"10300603","file_size":null,"low_hash":"f8f3559993dabc0536311525e57a8c34","whole_hash":"f8f3559993dabc0536311525e57a8c34","content_hash":"f8f3559993dabc0536311525e57a8c34","content_size":"10300603","lock_lrc":null,"year_play":"4","grade":"-1"},{"song_id":"1770874353","album_id":"78399","name":"Revolution (Mama Rose)","style":null,"track":"2","artist_name":"Archie Shepp","artist_id":"11392","lyric":null,"inkui_url":"/11392/78399/1770874353.mp3","songwriters":"","composer":"","threads_count":"0","posts_count":"0","listen_file":"/aliyunos/392/11392/78399/1770874353_3235169_l.mp3","lyric_url":"0","has_resource":null,"cd_serial":"1","sub_title":null,"complete":"1","singers":"Archie Shepp","arrangement":"","default_resource_id":"3235169","lyric_file":null,"title_url":"Gemini","length":"632","recommends":"3","title":"Gemini","gmt_publish":"1183910400","picture":null,"song_count":"16","language":"英语","publishtime":"Jul 9, 2007","inkui_img_url":null,"company":"Archie Ball","disc_code":"","rank":"0","album_logo":"http://img.xiami.net/./res/img/default/cd55.gif","is_check":"0","category":null,"status":"1","album_url":"/cg/amg.dll?p=amg\u0026amp;sql=10:j9fixzqgldte","category_name":null,"cd_count":"2","is_play":"1","uploader":null,"gmt_upload":"0","is_exported":"0","editor":null,"gmt_add":"0","gmt_last_modified":"0","key_words":" ","tags":";","tw_top":"0","crawler":null,"xiami_pub_id":"294444","collects":"10","play_count":"56","pub_bitrate":"0","genre_id":null,"encode_rate":"0","location":"http://m1.file.xiami.com/392/11392/78399/1770874353_3235169_l.mp3","low_size":"25279215","file_size":null,"low_hash":"48bba503b114f1375bf58a087109fdfd","whole_hash":"48bba503b114f1375bf58a087109fdfd","content_hash":"48bba503b114f1375bf58a087109fdfd","content_size":"25279215","lock_lrc":null,"year_play":"6","grade":"-1"},{"song_id":"1770874354","album_id":"78399","name":"Burning Bright","style":null,"track":"3","artist_name":"Archie Shepp","artist_id":"11392","lyric":null,"inkui_url":"/11392/78399/1770874354.mp3","songwriters":"","composer":"","threads_count":"0","posts_count":"0","listen_file":"/aliyunos/392/11392/78399/1770874354_3235170_l.mp3","lyric_url":"0","has_resource":null,"cd_serial":"1","sub_title":null,"complete":"1","singers":"Archie Shepp","arrangement":"","default_resource_id":"3235170","lyric_file":null,"title_url":"Gemini","length":"365","recommends":"3","title":"Gemini","gmt_publish":"1183910400","picture":null,"song_count":"16","language":"英语","publishtime":"Jul 9, 2007","inkui_img_url":null,"company":"Archie Ball","disc_code":"","rank":"0","album_logo":"http://img.xiami.net/./res/img/default/cd55.gif","is_check":"0","category":null,"status":"1","album_url":"/cg/amg.dll?p=amg\u0026amp;sql=10:j9fixzqgldte","category_name":null,"cd_count":"2","is_play":"1","uploader":null,"gmt_upload":"0","is_exported":"0","editor":null,"gmt_add":"0","gmt_last_modified":"0","key_words":" ","tags":";","tw_top":"0","crawler":null,"xiami_pub_id":"294444","collects":"10","play_count":"56","pub_bitrate":"0","genre_id":null,"encode_rate":"0","location":"http://m1.file.xiami.com/392/11392/78399/1770874354_3235170_l.mp3","low_size":"14627525","file_size":null,"low_hash":"9fb39a3ea43d1c613285cc7667dafced","whole_hash":"9fb39a3ea43d1c613285cc7667dafced","content_hash":"9fb39a3ea43d1c613285cc7667dafced","content_size":"14627525","lock_lrc":null,"year_play":"5","grade":"-1"},{"song_id":"1770874355","album_id":"78399","name":"Trippin\u0026#039;","style":null,"track":"4","artist_name":"Archie Shepp","artist_id":"11392","lyric":null,"inkui_url":"/11392/78399/1770874355.mp3","songwriters":"","composer":"","threads_count":"0","posts_count":"0","listen_file":"/aliyunos/392/11392/78399/1770874355_3235171_l.mp3","lyric_url":"0","has_resource":null,"cd_serial":"1","sub_title":null,"complete":"1","singers":"Archie Shepp","arrangement":"","default_resource_id":"3235171","lyric_file":null,"title_url":"Gemini","length":"281","recommends":"3","title":"Gemini","gmt_publish":"1183910400","picture":null,"song_count":"16","language":"英语","publishtime":"Jul 9, 2007","inkui_img_url":null,"company":"Archie Ball","disc_code":"","rank":"0","album_logo":"http://img.xiami.net/./res/img/default/cd55.gif","is_check":"0","category":null,"status":"1","album_url":"/cg/amg.dll?p=amg\u0026amp;sql=10:j9fixzqgldte","category_name":null,"cd_count":"2","is_play":"1","uploader":null,"gmt_upload":"0","is_exported":"0","editor":null,"gmt_add":"0","gmt_last_modified":"0","key_words":" ","tags":";","tw_top":"0","crawler":null,"xiami_pub_id":"294444","collects":"10","play_count":"56","pub_bitrate":"0","genre_id":null,"encode_rate":"0","location":"http://m1.file.xiami.com/392/11392/78399/1770874355_3235171_l.mp3","low_size":"11242056","file_size":null,"low_hash":"ce466bc4e04da18a4ec6a8ae04b4cf3a","whole_hash":"ce466bc4e04da18a4ec6a8ae04b4cf3a","content_hash":"ce466bc4e04da18a4ec6a8ae04b4cf3a","content_size":"11242056","lock_lrc":null,"year_play":"6","grade":"-1"},{"song_id":"1770874356","album_id":"78399","name":"Time Stood Still","style":null,"track":"5","artist_name":"Archie Shepp","artist_id":"11392","lyric":null,"inkui_url":"/11392/78399/1770874356.mp3","songwriters":"","composer":"","threads_count":"0","posts_count":"0","listen_file":"/aliyunos/392/11392/78399/1770874356_3235172_l.mp3","lyric_url":"0","has_resource":null,"cd_serial":"1","sub_title":null,"complete":"1","singers":"Archie Shepp","arrangement":"","default_resource_id":"3235172","lyric_file":null,"title_url":"Gemini","length":"415","recommends":"3","title":"Gemini","gmt_publish":"1183910400","picture":null,"song_count":"16","language":"英语","publishtime":"Jul 9, 2007","inkui_img_url":null,"company":"Archie Ball","disc_code":"","rank":"0","album_logo":"http://img.xiami.net/./res/img/default/cd55.gif","is_check":"0","category":null,"status":"1","album_url":"/cg/amg.dll?p=amg\u0026amp;sql=10:j9fixzqgldte","category_name":null,"cd_count":"2","is_play":"1","uploader":null,"gmt_upload":"0","is_exported":"0","editor":null,"gmt_add":"0","gmt_last_modified":"0","key_words":" ","tags":";","tw_top":"0","crawler":null,"xiami_pub_id":"294444","collects":"10","play_count":"56","pub_bitrate":"0","genre_id":null,"encode_rate":"0","location":"http://m1.file.xiami.com/392/11392/78399/1770874356_3235172_l.mp3","low_size":"16599248","file_size":null,"low_hash":"a9b8a1ae8e45f19e85e8cd2bfc01c448","whole_hash":"a9b8a1ae8e45f19e85e8cd2bfc01c448","content_hash":"a9b8a1ae8e45f19e85e8cd2bfc01c448","content_size":"16599248","lock_lrc":null,"year_play":"3","grade":"-1"},{"song_id":"1770874357","album_id":"78399","name":"Intertwining Spirits","style":null,"track":"6","artist_name":"Archie Shepp","artist_id":"11392","lyric":null,"inkui_url":"/11392/78399/1770874357.mp3","songwriters":"","composer":"","threads_count":"0","posts_count":"0","listen_file":"/aliyunos/392/11392/78399/1770874357_3235173_l.mp3","lyric_url":"0","has_resource":null,"cd_serial":"1","sub_title":null,"complete":"1","singers":"Archie Shepp","arrangement":"","default_resource_id":"3235173","lyric_file":null,"title_url":"Gemini","length":"446","recommends":"3","title":"Gemini","gmt_publish":"1183910400","picture":null,"song_count":"16","language":"英语","publishtime":"Jul 9, 2007","inkui_img_url":null,"company":"Archie Ball","disc_code":"","rank":"0","album_logo":"http://img.xiami.net/./res/img/default/cd55.gif","is_check":"0","category":null,"status":"1","album_url":"/cg/amg.dll?p=amg\u0026amp;sql=10:j9fixzqgldte","category_name":null,"cd_count":"2","is_play":"1","uploader":null,"gmt_upload":"0","is_exported":"0","editor":null,"gmt_add":"0","gmt_last_modified":"0","key_words":" ","tags":";","tw_top":"0","crawler":null,"xiami_pub_id":"294444","collects":"10","play_count":"56","pub_bitrate":"0","genre_id":null,"encode_rate":"0","location":"http://m1.file.xiami.com/392/11392/78399/1770874357_3235173_l.mp3","low_size":"17831182","file_size":null,"low_hash":"6c5cb81973b99b54f899fee113938024","whole_hash":"6c5cb81973b99b54f899fee113938024","content_hash":"6c5cb81973b99b54f899fee113938024","content_size":"17831182","lock_lrc":null,"year_play":"4","grade":"-1"},{"song_id":"1770874358","album_id":"78399","name":"La Manzana","style":null,"track":"7","artist_name":"Archie Shepp","artist_id":"11392","lyric":null,"inkui_url":"/11392/78399/1770874358.mp3","songwriters":"","composer":"","threads_count":"0","posts_count":"0","listen_file":"/aliyunos/392/11392/78399/1770874358_3235174_l.mp3","lyric_url":"0","has_resource":null,"cd_serial":"1","sub_title":null,"complete":"1","singers":"Archie Shepp","arrangement":"","default_resource_id":"3235174","lyric_file":null,"title_url":"Gemini","length":"319","recommends":"3","title":"Gemini","gmt_publish":"1183910400","picture":null,"song_count":"16","language":"英语","publishtime":"Jul 9, 2007","inkui_img_url":null,"company":"Archie Ball","disc_code":"","rank":"0","album_logo":"http://img.xiami.net/./res/img/default/cd55.gif","is_check":"0","category":null,"status":"1","album_url":"/cg/amg.dll?p=amg\u0026amp;sql=10:j9fixzqgldte","category_name":null,"cd_count":"2","is_play":"1","uploader":null,"gmt_upload":"0","is_exported":"0","editor":null,"gmt_add":"0","gmt_last_modified":"0","key_words":" ","tags":";","tw_top":"0","crawler":null,"xiami_pub_id":"294444","collects":"10","play_count":"56","pub_bitrate":"0","genre_id":null,"encode_rate":"0","location":"http://m1.file.xiami.com/392/11392/78399/1770874358_3235174_l.mp3","low_size":"12760293","file_size":null,"low_hash":"a3b069399105e35acc8410e98971879e","whole_hash":"a3b069399105e35acc8410e98971879e","content_hash":"a3b069399105e35acc8410e98971879e","content_size":"12760293","lock_lrc":null,"year_play":"2","grade":"-1"},{"song_id":"1770874359","album_id":"78399","name":"Eva","style":null,"track":"8","artist_name":"Archie Shepp","artist_id":"11392","lyric":null,"inkui_url":"/11392/78399/1770874359.mp3","songwriters":"","composer":"","threads_count":"0","posts_count":"0","listen_file":"/aliyunos/392/11392/78399/1770874359_3235175_l.mp3","lyric_url":"0","has_resource":null,"cd_serial":"1","sub_title":null,"complete":"1","singers":"Archie Shepp","arrangement":"","default_resource_id":"3235175","lyric_file":null,"title_url":"Gemini","length":"410","recommends":"3","title":"Gemini","gmt_publish":"1183910400","picture":null,"song_count":"16","language":"英语","publishtime":"Jul 9, 2007","inkui_img_url":null,"company":"Archie Ball","disc_code":"","rank":"0","album_logo":"http://img.xiami.net/./res/img/default/cd55.gif","is_check":"0","category":null,"status":"1","album_url":"/cg/amg.dll?p=amg\u0026amp;sql=10:j9fixzqgldte","category_name":null,"cd_count":"2","is_play":"1","uploader":null,"gmt_upload":"0","is_exported":"0","editor":null,"gmt_add":"0","gmt_last_modified":"0","key_words":" ","tags":";","tw_top":"0","crawler":null,"xiami_pub_id":"294444","collects":"10","play_count":"56","pub_bitrate":"0","genre_id":null,"encode_rate":"0","location":"http://m1.file.xiami.com/392/11392/78399/1770874359_3235175_l.mp3","low_size":"16406986","file_size":null,"low_hash":"9de5b57783345d988168911454581d7a","whole_hash":"9de5b57783345d988168911454581d7a","content_hash":"9de5b57783345d988168911454581d7a","content_size":"16406986","lock_lrc":null,"year_play":"3","grade":"-1"},{"song_id":"1770874360","album_id":"78399","name":"Pannonica","style":null,"track":"9","artist_name":"Archie Shepp","artist_id":"11392","lyric":null,"inkui_url":"/11392/78399/1770874360.mp3","songwriters":"","composer":"","threads_count":"0","posts_count":"0","listen_file":"/aliyunos/392/11392/78399/1770874360_3235177_l.mp3","lyric_url":"0","has_resource":null,"cd_serial":"1","sub_title":null,"complete":"1","singers":"Archie Shepp","arrangement":"","default_resource_id":"3235177","lyric_file":null,"title_url":"Gemini","length":"310","recommends":"3","title":"Gemini","gmt_publish":"1183910400","picture":null,"song_count":"16","language":"英语","publishtime":"Jul 9, 2007","inkui_img_url":null,"company":"Archie Ball","disc_code":"","rank":"0","album_logo":"http://img.xiami.net/./res/img/default/cd55.gif","is_check":"0","category":null,"status":"1","album_url":"/cg/amg.dll?p=amg\u0026amp;sql=10:j9fixzqgldte","category_name":null,"cd_count":"2","is_play":"1","uploader":null,"gmt_upload":"0","is_exported":"0","editor":null,"gmt_add":"0","gmt_last_modified":"0","key_words":" ","tags":";","tw_top":"0","crawler":null,"xiami_pub_id":"294444","collects":"10","play_count":"56","pub_bitrate":"0","genre_id":null,"encode_rate":"0","location":"http://m1.file.xiami.com/392/11392/78399/1770874360_3235177_l.mp3","low_size":"12412342","file_size":null,"low_hash":"607216ce74eeeb8759c6df53b1565511","whole_hash":"607216ce74eeeb8759c6df53b1565511","content_hash":"607216ce74eeeb8759c6df53b1565511","content_size":"12412342","lock_lrc":null,"year_play":"4","grade":"-1"},{"song_id":"1770874361","album_id":"78399","name":"The Reverse","style":null,"track":"10","artist_name":"Archie Shepp","artist_id":"11392","lyric":null,"inkui_url":"/11392/78399/1770874361.mp3","songwriters":"","composer":"","threads_count":"0","posts_count":"0","listen_file":"/aliyunos/392/11392/78399/1770874361_3235178_l.mp3","lyric_url":"0","has_resource":null,"cd_serial":"1","sub_title":null,"complete":"1","singers":"Archie Shepp","arrangement":"","default_resource_id":"3235178","lyric_file":null,"title_url":"Gemini","length":"272","recommends":"3","title":"Gemini","gmt_publish":"1183910400","picture":null,"song_count":"16","language":"英语","publishtime":"Jul 9, 2007","inkui_img_url":null,"company":"Archie Ball","disc_code":"","rank":"0","album_logo":"http://img.xiami.net/./res/img/default/cd55.gif","is_check":"0","category":null,"status":"1","album_url":"/cg/amg.dll?p=amg\u0026amp;sql=10:j9fixzqgldte","category_name":null,"cd_count":"2","is_play":"1","uploader":null,"gmt_upload":"0","is_exported":"0","editor":null,"gmt_add":"0","gmt_last_modified":"0","key_words":" ","tags":";","tw_top":"0","crawler":null,"xiami_pub_id":"294444","collects":"10","play_count":"56","pub_bitrate":"0","genre_id":null,"encode_rate":"0","location":"http://m1.file.xiami.com/392/11392/78399/1770874361_3235178_l.mp3","low_size":"10887835","file_size":null,"low_hash":"c2447bcaab74cd9fc42984feae17273d","whole_hash":"c2447bcaab74cd9fc42984feae17273d","content_hash":"c2447bcaab74cd9fc42984feae17273d","content_size":"10887835","lock_lrc":null,"year_play":"3","grade":"-1"},{"song_id":"1770874362","album_id":"78399","name":"The Reverse (Alternate Version 2)","style":null,"track":"11","artist_name":"Archie Shepp","artist_id":"11392","lyric":null,"inkui_url":"/11392/78399/1770874362.mp3","songwriters":"","composer":"","threads_count":"0","posts_count":"0","listen_file":"/aliyunos/392/11392/78399/1770874362_3235179_l.mp3","lyric_url":"0","has_resource":null,"cd_serial":"1","sub_title":null,"complete":"1","singers":"Archie Shepp","arrangement":"","default_resource_id":"3235179","lyric_file":null,"title_url":"Gemini","length":"261","recommends":"3","title":"Gemini","gmt_publish":"1183910400","picture":null,"song_count":"16","language":"英语","publishtime":"Jul 9, 2007","inkui_img_url":null,"company":"Archie Ball","disc_code":"","rank":"0","album_logo":"http://img.xiami.net/./res/img/default/cd55.gif","is_check":"0","category":null,"status":"1","album_url":"/cg/amg.dll?p=amg\u0026amp;sql=10:j9fixzqgldte","category_name":null,"cd_count":"2","is_play":"1","uploader":null,"gmt_upload":"0","is_exported":"0","editor":null,"gmt_add":"0","gmt_last_modified":"0","key_words":" ","tags":";","tw_top":"0","crawler":null,"xiami_pub_id":"294444","collects":"10","play_count":"56","pub_bitrate":"0","genre_id":null,"encode_rate":"0","location":"http://m1.file.xiami.com/392/11392/78399/1770874362_3235179_l.mp3","low_size":"10446888","file_size":null,"low_hash":"87295f0dfcd47ef6a10b22f771b1a32c","whole_hash":"87295f0dfcd47ef6a10b22f771b1a32c","content_hash":"87295f0dfcd47ef6a10b22f771b1a32c","content_size":"10446888","lock_lrc":null,"year_play":"3","grade":"-1"},{"song_id":"1770874363","album_id":"78399","name":"Hope Two","style":null,"track":"1","artist_name":"Archie Shepp","artist_id":"11392","lyric":null,"inkui_url":"/11392/78399/1770874363.mp3","songwriters":"","composer":"","threads_count":"0","posts_count":"0","listen_file":"/aliyunos/392/11392/78399/1770874363_3235180_l.mp3","lyric_url":"0","has_resource":null,"cd_serial":"2","sub_title":null,"complete":"1","singers":"Archie Shepp","arrangement":"","default_resource_id":"3235180","lyric_file":null,"title_url":"Gemini","length":"669","recommends":"3","title":"Gemini","gmt_publish":"1183910400","picture":null,"song_count":"16","language":"英语","publishtime":"Jul 9, 2007","inkui_img_url":null,"company":"Archie Ball","disc_code":"","rank":"0","album_logo":"http://img.xiami.net/./res/img/default/cd55.gif","is_check":"0","category":null,"status":"1","album_url":"/cg/amg.dll?p=amg\u0026amp;sql=10:j9fixzqgldte","category_name":null,"cd_count":"2","is_play":"1","uploader":null,"gmt_upload":"0","is_exported":"0","editor":null,"gmt_add":"0","gmt_last_modified":"0","key_words":" ","tags":";","tw_top":"0","crawler":null,"xiami_pub_id":"294444","collects":"10","play_count":"56","pub_bitrate":"0","genre_id":null,"encode_rate":"0","location":"http://m1.file.xiami.com/392/11392/78399/1770874363_3235180_l.mp3","low_size":"26739982","file_size":null,"low_hash":"fab128e0946f8d6e13e763a5571b90e0","whole_hash":"fab128e0946f8d6e13e763a5571b90e0","content_hash":"fab128e0946f8d6e13e763a5571b90e0","content_size":"26739982","lock_lrc":null,"year_play":"3","grade":"-1"},{"song_id":"1770874364","album_id":"78399","name":"Call Him","style":null,"track":"2","artist_name":"Archie Shepp","artist_id":"11392","lyric":null,"inkui_url":"/11392/78399/1770874364.mp3","songwriters":"","composer":"","threads_count":"0","posts_count":"0","listen_file":"/aliyunos/392/11392/78399/1770874364_3235181_l.mp3","lyric_url":"0","has_resource":null,"cd_serial":"2","sub_title":null,"complete":"1","singers":"Archie Shepp","arrangement":"","default_resource_id":"3235181","lyric_file":null,"title_url":"Gemini","length":"330","recommends":"3","title":"Gemini","gmt_publish":"1183910400","picture":null,"song_count":"16","language":"英语","publishtime":"Jul 9, 2007","inkui_img_url":null,"company":"Archie Ball","disc_code":"","rank":"0","album_logo":"http://img.xiami.net/./res/img/default/cd55.gif","is_check":"0","category":null,"status":"1","album_url":"/cg/amg.dll?p=amg\u0026amp;sql=10:j9fixzqgldte","category_name":null,"cd_count":"2","is_play":"1","uploader":null,"gmt_upload":"0","is_exported":"0","editor":null,"gmt_add":"0","gmt_last_modified":"0","key_words":" ","tags":";","tw_top":"0","crawler":null,"xiami_pub_id":"294444","collects":"10","play_count":"56","pub_bitrate":"0","genre_id":null,"encode_rate":"0","location":"http://m1.file.xiami.com/392/11392/78399/1770874364_3235181_l.mp3","low_size":"13200195","file_size":null,"low_hash":"7e1f7ace85d3dce12fe96dba9cc40d70","whole_hash":"7e1f7ace85d3dce12fe96dba9cc40d70","content_hash":"7e1f7ace85d3dce12fe96dba9cc40d70","content_size":"13200195","lock_lrc":null,"year_play":"3","grade":"-1"},{"song_id":"1770874365","album_id":"78399","name":"Do You Want To Be Saved","style":null,"track":"3","artist_name":"Archie Shepp","artist_id":"11392","lyric":null,"inkui_url":"/11392/78399/1770874365.mp3","songwriters":"","composer":"","threads_count":"0","posts_count":"0","listen_file":"/aliyunos/392/11392/78399/1770874365_3235182_l.mp3","lyric_url":"0","has_resource":null,"cd_serial":"2","sub_title":null,"complete":"1","singers":"Archie Shepp","arrangement":"","default_resource_id":"3235182","lyric_file":null,"title_url":"Gemini","length":"440","recommends":"3","title":"Gemini","gmt_publish":"1183910400","picture":null,"song_count":"16","language":"英语","publishtime":"Jul 9, 2007","inkui_img_url":null,"company":"Archie Ball","disc_code":"","rank":"0","album_logo":"http://img.xiami.net/./res/img/default/cd55.gif","is_check":"0","category":null,"status":"1","album_url":"/cg/amg.dll?p=amg\u0026amp;sql=10:j9fixzqgldte","category_name":null,"cd_count":"2","is_play":"1","uploader":null,"gmt_upload":"0","is_exported":"0","editor":null,"gmt_add":"0","gmt_last_modified":"0","key_words":" ","tags":";","tw_top":"0","crawler":null,"xiami_pub_id":"294444","collects":"10","play_count":"56","pub_bitrate":"0","genre_id":null,"encode_rate":"0","location":"http://m1.file.xiami.com/392/11392/78399/1770874365_3235182_l.mp3","low_size":"17619068","file_size":null,"low_hash":"fdcc458b570339017f2a5cab426f695a","whole_hash":"fdcc458b570339017f2a5cab426f695a","content_hash":"fdcc458b570339017f2a5cab426f695a","content_size":"17619068","lock_lrc":null,"year_play":"2","grade":"-1"},{"song_id":"1770874366","album_id":"78399","name":"Ujaama","style":null,"track":"4","artist_name":"Archie Shepp","artist_id":"11392","lyric":null,"inkui_url":"/11392/78399/1770874366.mp3","songwriters":"","composer":"","threads_count":"0","posts_count":"0","listen_file":"/aliyunos/392/11392/78399/1770874366_3235183_l.mp3","lyric_url":"0","has_resource":null,"cd_serial":"2","sub_title":null,"complete":"1","singers":"Archie Shepp","arrangement":"","default_resource_id":"3235183","lyric_file":null,"title_url":"Gemini","length":"803","recommends":"3","title":"Gemini","gmt_publish":"1183910400","picture":null,"song_count":"16","language":"英语","publishtime":"Jul 9, 2007","inkui_img_url":null,"company":"Archie Ball","disc_code":"","rank":"0","album_logo":"http://img.xiami.net/./res/img/default/cd55.gif","is_check":"0","category":null,"status":"1","album_url":"/cg/amg.dll?p=amg\u0026amp;sql=10:j9fixzqgldte","category_name":null,"cd_count":"2","is_play":"1","uploader":null,"gmt_upload":"0","is_exported":"0","editor":null,"gmt_add":"0","gmt_last_modified":"0","key_words":" ","tags":";","tw_top":"0","crawler":null,"xiami_pub_id":"294444","collects":"10","play_count":"56","pub_bitrate":"0","genre_id":null,"encode_rate":"0","location":"http://m1.file.xiami.com/392/11392/78399/1770874366_3235183_l.mp3","low_size":"32130611","file_size":null,"low_hash":"b62a15417dc212fbfb084b7ed21986c3","whole_hash":"b62a15417dc212fbfb084b7ed21986c3","content_hash":"b62a15417dc212fbfb084b7ed21986c3","content_size":"32130611","lock_lrc":null,"year_play":"2","grade":"-1"},{"song_id":"1770874367","album_id":"78399","name":"Rest Enough","style":null,"track":"5","artist_name":"Archie Shepp","artist_id":"11392","lyric":null,"inkui_url":"/11392/78399/1770874367.mp3","songwriters":"","composer":"","threads_count":"0","posts_count":"0","listen_file":"/aliyunos/392/11392/78399/1770874367_3235184_l.mp3","lyric_url":"0","has_resource":null,"cd_serial":"2","sub_title":null,"complete":"1","singers":"Archie Shepp","arrangement":"","default_resource_id":"3235184","lyric_file":null,"title_url":"Gemini","length":"242","recommends":"3","title":"Gemini","gmt_publish":"1183910400","picture":null,"song_count":"16","language":"英语","publishtime":"Jul 9, 2007","inkui_img_url":null,"company":"Archie Ball","disc_code":"","rank":"0","album_logo":"http://img.xiami.net/./res/img/default/cd55.gif","is_check":"0","category":null,"status":"1","album_url":"/cg/amg.dll?p=amg\u0026amp;sql=10:j9fixzqgldte","category_name":null,"cd_count":"2","is_play":"1","uploader":null,"gmt_upload":"0","is_exported":"0","editor":null,"gmt_add":"0","gmt_last_modified":"0","key_words":" ","tags":";","tw_top":"0","crawler":null,"xiami_pub_id":"294444","collects":"10","play_count":"56","pub_bitrate":"0","genre_id":null,"encode_rate":"0","location":"http://m1.file.xiami.com/392/11392/78399/1770874367_3235184_l.mp3","low_size":"9683068","file_size":null,"low_hash":"770bba40449979c181422c659dcc083c","whole_hash":"770bba40449979c181422c659dcc083c","content_hash":"770bba40449979c181422c659dcc083c","content_size":"9683068","lock_lrc":null,"year_play":"3","grade":"-1"}]